{
  "cartridge": [],
  "cartridgePath": [],
  "clean": false,
  "defaultLocale": "default",
  "exclude": [],
  "js": {
    "aliasDir": "js",
    "inputPath": "cartridges/{cartridge}/cartridge/client/default/js",
    "outputPath": "cartridges/{cartridge}/cartridge/static/default/js"
  },
  "mainDir": "client",
  "mainEntry": "main",
  "mainFiles": [
    "main.js"
  ],
  "revolverExclude": [],
  "rootFiles": true,
  "scope": "js",
  "scss": {
    "aliasDir": "scss",
    "includePaths": [
      "node_modules/flag-icon-css/sass"
    ],
    "inputPath": "cartridges/{cartridge}/cartridge/client/**/*.scss",
    "keepOriginalLocation": true,
    "outputPath": "cartridges/{cartridge}/cartridge/static"
  },
  "sites": {},
  "site": "",
  "useLocales": true
}
